[
  {
    "id": 1,
    "code": "5451",
    "title": "Newsletter Discount",
    "description": "&lt;p&gt;\n\tsadasd&lt;\/p&gt;&lt;p&gt;\n\tasdasdas&lt;\/p&gt;",
    "discount": "15.00",
    "discount_type": "%",
    "productid": "0",
    "categoryid": "3",
    "minimum": "0.00",
    "times": 0,
    "per_user": "N",
    "times_used": 0,
    "expire": "2016-11-17 10:59:30",
    "active": 1,
    "uid": 1,
    "recursive": "N",
    "apply_category_once": "N",
    "apply_product_once": "N",
    "settings": "false",
    "created_at": null,
    "updated_at": "2014-07-18 12:20:10"
  },
  {
    "id": 2,
    "code": "5452",
    "title": "10% discount",
    "description": "&lt;p&gt;&amp;lt;p&amp;gt;&amp;lt;p&amp;gt;sssd&amp;lt;\/p&amp;gt;&amp;lt;\/p&amp;gt;&lt;\/p&gt;",
    "discount": "10.00",
    "discount_type": "%",
    "productid": "12",
    "categoryid": "0",
    "minimum": "1.00",
    "times": 0,
    "per_user": "N",
    "times_used": 1,
    "expire": "2015-06-19 09:22:14",
    "active": 1,
    "uid": 0,
    "recursive": "Y",
    "apply_category_once": "N",
    "apply_product_once": "N",
    "settings": "",
    "created_at": null,
    "updated_at": null
  },
  {
    "id": 3,
    "code": "5453",
    "title": "Free shipping",
    "description": "&lt;p&gt;aaa sa sas &lt;\/p&gt;",
    "discount": "0.00",
    "discount_type": "free_ship",
    "productid": "0",
    "categoryid": "0",
    "minimum": "0.00",
    "times": 20,
    "per_user": "Y",
    "times_used": 3,
    "expire": "2014-06-26 09:22:32",
    "active": 1,
    "uid": 0,
    "recursive": "",
    "apply_category_once": "",
    "apply_product_once": "",
    "settings": "",
    "created_at": null,
    "updated_at": "2014-07-18 12:14:29"
  }
]